pychattr/__init__.py
pychattr/channel_attribution/__init__.py
pychattr/channel_attribution/_heuristic.py
pychattr/channel_attribution/_markov.py
pychattr/channel_attribution/_mixins.py
pychattr/channel_attribution/heuristic.py
pychattr/channel_attribution/markov.py
pychattr-0.2.1.dist-info/LICENSE
pychattr-0.2.1.dist-info/METADATA
pychattr-0.2.1.dist-info/WHEEL
pychattr-0.2.1.dist-info/top_level.txt
pychattr-0.2.1.dist-info/RECORD
