Metadata-Version: 2.1
Name: pychattr
Version: 0.2.1
Summary: Python Channel Attribution
Home-page: https://github.com/jmwoloso/pychattr
Author: Jason Wolosonovich
Author-email: jason@refinerynet.com
License: BSD 3-clause
Platform: UNKNOWN
Classifier: Development Status :: 3 - Alpha
Classifier: Programming Language :: Python :: 3
Classifier: Topic :: Software Development :: Libraries :: Python Modules
Classifier: Topic :: Scientific/Engineering
Classifier: Operating System :: Unix
Classifier: Operating System :: MacOS
Classifier: Operating System :: POSIX
Classifier: Operating System :: Microsoft :: Windows
Classifier: Intended Audience :: Science/Research
Classifier: Intended Audience :: Other Audience
Classifier: Intended Audience :: Information Technology
Requires-Dist: numpy
Requires-Dist: pandas
